battery_mcp/__init__.py
battery_mcp/__main__.py
battery_mcp/db.py
battery_mcp/http_server.py
battery_mcp/server.py
battery_mcp/tools.py
battery_mcp-0.0.3.dist-info/METADATA
battery_mcp-0.0.3.dist-info/WHEEL
battery_mcp-0.0.3.dist-info/entry_points.txt
battery_mcp-0.0.3.dist-info/RECORD
