Metadata-Version: 2.4
Name: battery-mcp
Version: 0.0.3
Summary: A Model Context Protocol server providing tools to search and verify battery materials
Author: Menlo Research
Maintainer-email: Alex Nguyen <alex@menlo.ai>
License: MIT
Keywords: automation,http,llm,mcp
Classifier: Development Status :: 4 - Beta
Classifier: Intended Audience :: Developers
Classifier: License :: OSI Approved :: MIT License
Classifier: Programming Language :: Python :: 3
Classifier: Programming Language :: Python :: 3.10
Requires-Python: >=3.10
Requires-Dist: chatbattery
Requires-Dist: httpx<0.28
Requires-Dist: markdownify>=0.13.1
Requires-Dist: mcp>=1.1.3
Requires-Dist: mp-api==0.41.2
Requires-Dist: pandas
Requires-Dist: protego>=0.3.1
Requires-Dist: pydantic>=2.0.0
Requires-Dist: readabilipy>=0.2.0
Requires-Dist: requests>=2.32.3
